{"stats":{"minecraft:dropped":{"minecraft:wheat_seeds":1,"minecraft:iron_nugget":4,"minecraft:spruce_planks":1,"minecraft:tnt":2,"alexsmobs:animal_dictionary":4,"minecraft:skeleton_skull":2,"cyclic:crystal_pickaxe":2,"minecraft:crafting_table":1,"minecraft:stripped_crimson_hyphae":1,"deeperdarker:resonarium_pickaxe":1},"minecraft:crafted":{"minecraft:oak_planks":76,"tombstone:grave_key":1,"minecraft:crafting_table":2,"minecraft:spruce_planks":32,"minecraft:stick":28,"cyclic:crafting_stick":1},"minecraft:killed_by":{"creeperoverhaul:ocean_creeper":1,"minecraft:vindicator":2,"minecraft:player":3,"mimicer:mimicer":1},"minecraft:picked_up":{"minecraft:stripped_crimson_hyphae":1,"cyclic:crystal_pickaxe":1,"minecraft:oak_log":1,"deeperdarker:resonarium_pickaxe":1,"alexsmobs:animal_dictionary":3,"minecraft:tnt":2,"minecraft:oak_wood":23,"minecraft:quartz_block":2,"minecraft:arrow":2,"minecraft:wheat_seeds":1,"minecraft:melon_slice":9,"minecraft:oak_planks":7,"minecraft:white_wool":17},"minecraft:used":{"minecraft:water_bucket":2,"minecraft:oak_planks":31,"minecraft:melon_slice":9,"minecraft:spruce_planks":9,"minecraft:white_wool":4,"simplyswords:gold_cutlass":14,"minecraft:iron_chestplate":1,"minecraft:anvil":1,"minecraft:cooked_cod":1,"minecraft:porkchop":2,"minecraft:bucket":2,"tombstone:gift":5,"alexsmobs:animal_dictionary":1,"tinkers_thinking:paxel":5},"minecraft:custom":{"minecraft:time_since_rest":601,"lootr:looted_stat":12,"minecraft:sprint_one_cm":43156,"minecraft:damage_taken":3605,"minecraft:walk_one_cm":45791,"minecraft:interact_with_anvil":1,"minecraft:mob_kills":1,"minecraft:drop":15,"minecraft:damage_dealt":1517,"minecraft:swim_one_cm":10635,"minecraft:player_kills":2,"minecraft:fly_one_cm":66429,"minecraft:crouch_one_cm":14279,"waystones:waystone_activated":1,"minecraft:play_time":37209,"minecraft:deaths":9,"minecraft:sneak_time":3601,"minecraft:walk_under_water_one_cm":9976,"minecraft:jump":549,"minecraft:leave_game":4,"minecraft:walk_on_water_one_cm":4632,"minecraft:time_since_death":578,"minecraft:total_world_time":37209,"minecraft:climb_one_cm":1319,"minecraft:fall_one_cm":15149},"minecraft:killed":{"creeperoverhaul:ocean_creeper":1},"minecraft:mined":{"minecraft:tall_seagrass":1,"minecraft:quartz_block":3,"minecraft:fire":6,"minecraft:tnt":4,"minecraft:oak_wood":19,"minecraft:grass":2,"minecraft:stripped_crimson_hyphae":1,"minecraft:oak_log":1,"minecraft:melon":2,"minecraft:white_wool":1,"minecraft:oak_planks":4,"minecraft:oak_leaves":4,"minecraft:fern":6,"minecraft:spawner":1}},"DataVersion":3465}